plmbr/__init__.py
plmbr/columns.py
plmbr/core.py
plmbr/filters.py
plmbr/py.typed
plmbr/transformers.py
plmbr-0.1.0.dist-info/METADATA
plmbr-0.1.0.dist-info/WHEEL
plmbr-0.1.0.dist-info/RECORD
