Metadata-Version: 2.4
Name: plmbr
Version: 0.1.0
Summary: create data processing pipelines
Author-email: Deekshant Yadav <d33kshant@gmail.com>
Requires-Python: >=3.13
Requires-Dist: pandas>=2.2.3
